modernauth/__init__.py
modernauth/admin.py
modernauth/apps.py
modernauth/models.py
modernauth/tests.py
modernauth/views.py
modernauth/migrations/0001_initial.py
modernauth/migrations/__init__.py
django_rapyd_modernauth-0.0.4.dist-info/LICENSE
django_rapyd_modernauth-0.0.4.dist-info/METADATA
django_rapyd_modernauth-0.0.4.dist-info/WHEEL
django_rapyd_modernauth-0.0.4.dist-info/top_level.txt
django_rapyd_modernauth-0.0.4.dist-info/RECORD
