Metadata-Version: 2.1
Name: django-rapyd-modernauth
Version: 0.0.4
Summary: A Django application that provides a custom User model where the username is the email address.
Home-page: https://github.com/karthicraghupathi/django_rapyd_modernauth
Author: "Karthic Raghupathi",
Author-email: "karthicr@gmail.com",
License: Apache Software License
Platform: UNKNOWN
Classifier: Environment :: Web Environment
Classifier: Intended Audience :: Developers
Classifier: License :: OSI Approved :: Apache Software License
Classifier: Operating System :: OS Independent
Classifier: Programming Language :: Python :: 3 :: Only
Classifier: Programming Language :: Python :: 3.6
Classifier: Programming Language :: Python :: 3.10
Classifier: Programming Language :: Python :: Implementation :: CPython
Classifier: Topic :: Software Development :: Libraries :: Application Frameworks
Classifier: Topic :: Software Development :: Libraries :: Python Modules
Requires-Python: >=3.6
License-File: LICENSE
Requires-Dist: Django (<3.3,>=3)
